weather_yang_mcp/__init__.py
weather_yang_mcp/__main__.py
weather_yang_mcp/weather_server.py
weather_yang_mcp-0.1.5.dist-info/LICENSE
weather_yang_mcp-0.1.5.dist-info/METADATA
weather_yang_mcp-0.1.5.dist-info/WHEEL
weather_yang_mcp-0.1.5.dist-info/entry_points.txt
weather_yang_mcp-0.1.5.dist-info/top_level.txt
weather_yang_mcp-0.1.5.dist-info/RECORD
