Metadata-Version: 2.1
Name: weather_yang_mcp
Version: 0.1.5
Summary: A get weather tool
Home-page: https://github.com/jokulyang/mytool
Author: jokul
Author-email: test@qq.com
Classifier: Programming Language :: Python :: 3
Classifier: License :: OSI Approved :: MIT License
Classifier: Operating System :: OS Independent
Classifier: Development Status :: 3 - Alpha
Classifier: Intended Audience :: Developers
Classifier: Topic :: Software Development :: Libraries :: Python Modules
Requires-Python: >=3.11
License-File: LICENSE
Requires-Dist: mcp>=1.9.0
Requires-Dist: pydantic>=2.0.0
Requires-Dist: tzdata>=2023.3
Requires-Dist: typing-extensions>=4.7.0
Requires-Dist: httpx>=0.24.0
